aioshim/__init__.py
aioshim/builtins.py
aioshim/itertools.py
aioshim-0.0.3.dist-info/DESCRIPTION.rst
aioshim-0.0.3.dist-info/METADATA
aioshim-0.0.3.dist-info/RECORD
aioshim-0.0.3.dist-info/WHEEL
aioshim-0.0.3.dist-info/entry_points.txt
aioshim-0.0.3.dist-info/metadata.json
aioshim-0.0.3.dist-info/top_level.txt
