Metadata-Version: 2.0
Name: aioshim
Version: 0.0.3
Summary: UNKNOWN
Home-page: https://github.com/feluxe/aioshim
Author: Felix Meyer-Wolters
Author-email: felix@meyerwolters.de
Maintainer: Felix Meyer-Wolters
Maintainer-email: felix@meyerwolters.de
License: unlicensed
Download-URL: https://github.com/feluxe/aioshim/tarball/0.0.3
Platform: 
Requires-Dist: aitertools
